adc_compliance_checker/__init__.py
adc_compliance_checker/checker.py
adc_compliance_checker/cli.py
tests/__init__.py
tests/test_checker.py
adc_compliance_checker-0.2.1.dist-info/LICENSE
adc_compliance_checker-0.2.1.dist-info/METADATA
adc_compliance_checker-0.2.1.dist-info/WHEEL
adc_compliance_checker-0.2.1.dist-info/entry_points.txt
adc_compliance_checker-0.2.1.dist-info/top_level.txt
adc_compliance_checker-0.2.1.dist-info/RECORD
