Metadata-Version: 2.1
Name: adc-compliance-checker
Version: 0.2.1
Summary: ADC Compliance Checker
Home-page: https://github.com/Alessimc/adc-compliance-checker
Author: Alessio Canclini
Author-email: alessioc@met.no
License: GPLv3
Platform: UNKNOWN
Classifier: Programming Language :: Python :: 3
Classifier: License :: OSI Approved :: GNU General Public License v3 (GPLv3)
Classifier: Operating System :: OS Independent
Requires-Python: >=3.6
License-File: LICENSE
Requires-Dist: h5netcdf
Requires-Dist: netCDF4
Requires-Dist: pathlib
Requires-Dist: xarray
